{"hash":"f180987ff9e7f783a5d7057468bad547c343e5ed","data":{"course":{"id":"1d5a45490dc8c1f484a51cced6991d7a","title":"Επισκόπηση","description":"Αυτό το μάθημα αφορά την εξοικείωση με το σύστημα Feecc και όλα τα στοιχεία του.","content":"\n## Σχετικά με το μάθημα\n\nΑυτό το μάθημα αφορά την εξοικείωση με το σύστημα Feecc και όλα τα στοιχεία του. Το Feecc είναι μια πλατφόρμα που επιτρέπει στις επιχειρήσεις να χτίσουν και να προσαρμόσουν το δικό τους σύστημα παρακολούθησης για τις διαδικασίες παραγωγής ή υπηρεσιών προκειμένου να ταιριάζει στις ανάγκες τους. Αναπτύσσεται από την [Multi-Agent Systems](http://multi-agent.io/) χρησιμοποιώντας τεχνολογίες που παρέχει η ομάδα Robonomics. Το μάθημα παρέχει βασικές γνώσεις για την αρχιτεκτονική του Feecc, συμπεριλαμβανομένου ενός σεναρίου επίδειξης, και εξηγεί πώς να αναπτύξετε και να χρησιμοποιήσετε αυτό το σύστημα. \n\n## Για ποιους είναι αυτό το μάθημα;\n\nΤο μάθημα απευθύνεται σε υπαλλήλους επιχειρήσεων που έχουν αποφασίσει να εφαρμόσουν το σύστημα παρακολούθησης παραγωγής Feecc, καθώς και σε ανώτερους μηχανικούς διοίκησης που αναζητούν νέες τεχνολογικές λύσεις για τη βελτίωση της ποιότητας των εργασιακών διαδικασιών.\n\n## Απαιτήσεις\n\nΤα υλικά του μαθήματος υποθέτουν βασικές δεξιότητες παραγωγικής μηχανικής, καθώς και δεξιότητες σε συστήματα βασισμένα σε UNIX. Η βασική γνώση του [Docker](https://www.docker.com/) είναι ευπρόσδεκτη.\n\n## Κύρια έννοια\n\nΧρησιμοποιώντας την τεχνολογία Web3 και ένα σύνολο ευέλικτων μονάδων λογισμικού, η πλατφόρμα Feecc επιτρέπει στις εταιρείες να οργανώνουν τη διαδικασία παραγωγής οποιουδήποτε τύπου προϊόντος, να ελέγχουν την πρόσβαση των εργαζομένων στο χώρο εργασίας και να ανακτούν όλα τα δεδομένα ροής εργασίας. Οι πληροφορίες αποθηκεύονται σε αμετάβλητο και ασφαλή κατανεμημένο χώρο αποθήκευσης IPFS, οι κατακερματισμοί δεδομένων αποθηκεύονται με τη μονάδα καταγραφής δεδομένων Robonomics με πρόσβαση για το τμήμα ποιοτικού ελέγχου μέσω του Feecc Analytics. Με το Feecc, μια εταιρεία μπορεί όχι μόνο να ψηφιοποιήσει τις διαδικασίες της και να απαλλαγεί από τη γραφειοκρατία και τις αγωγές, αλλά και να προσελκύσει την προσοχή νέων πελατών στο προϊόν, αυξάνοντας την εμπιστοσύνη σε αυτό.\n\nΗ πλατφόρμα αποτελείται από ένα σύνολο λογισμικού για την παρακολούθηση της διαδικασίας παραγωγής και τη συλλογή πληροφοριών για μετέπειτα ανάλυση από το QCD ή άλλους συμμετέχοντες. Παγκοσμίως, το σχήμα ενσωμάτωσης της πλατφόρμας στην επιχειρηματική διαδικασία μπορεί να αναπαρασταθεί ως εξής:\n\n<LessonImages src=\"feecc-course/feecc-scheme.jpg\" alt=\"A scheme of Feecc integration into the business process\"/>\n\n## Ευκαιρίες Πλατφόρμας\n\n- **Αξιόπιστη και ασφαλής αποθήκευση δεδομένων**: Η Feecc χρησιμοποιεί μια ασφαλή αποθήκευση δεδομένων βασισμένη σε μια αρχιτεκτονική με περιεχόμενο-διεύθυνση και ένα κατανεμημένο μητρώο για να εξασφαλίσει την αξιοπιστία και την εγκυρότητα των συλλεγμένων δεδομένων ροής εργασίας.\n\n- **Ένας σαφής σύνδεσμος μεταξύ του εργαζομένου και του προϊόντος**: Η Feecc παρακολουθεί όλες τις φάσεις της ροής εργασίας με εγγραφή βίντεο, καταγραφή δεδομένων από περιφερειακές συσκευές και εξουσιοδότηση πρόσβασης του εργαζομένου. Η πλατφόρμα υποστηρίζει οποιαδήποτε συνεχόμενη ροή εργασίας, συμπεριλαμβανομένων μακροχρόνιων ή διακοπών λειτουργιών.\n\n- **Ψηφιακό πιστοποιητικό προϊόντος**: Όλα α ψηφιακά ίχνη της ροής εργασίας συνοψίζονται σε ένα μοναδικό πιστοποιητικό προϊόντος με ένα μοναδικό αναγνωριστικό το οποίο στη συνέχεια προσαρτάται ως κωδικός QR στο προϊόν. Η Feecc μπορεί να προσθέσει προσαρμοσμένες παραμέτρους διαδικασίας στο πιστοποιητικό και να αυτοματοποιήσει τη δημιουργία του ακόμα και για σύνθετα μέρη.\n\n- **Εκτεταμένη υποστήριξη για περιφερειακές συσκευές**: Η Feecc υποστηρίζει τυπικές ψηφιακές διεπαφές εισόδου/εξόδου για τη σύνδεση διαφόρων συσκευών (βιντεοκάμερες, σαρωτές, εκτυπωτές, κλπ.).\n\nhttps://youtu.be/WhtOJtGjAok","fileInfo":{"path":"el/learn/feecc-course/overview.md","name":"overview"},"defaultName":"Getting Used to Feecc","lastUpdate":null}},"context":{}}