{"hash":"8d66541f6e2b7bde6cbd76ed09ec87c40b5569d7","data":{"course":{"id":"9a67dcb6b9c714e0f5d9f0fb1c05835f","title":"पाठ #7, गृह सहायक के साथ रोबोनॉमिक्स का उपयोग","description":"होम असिस्टेंट कोर्स","content":"\n## यह किसके बारे में है\n\nइस सबक में, आप मुख्य रोबोनॉमिक्स आईओटी सेवाओं का उपयोग करने का प्रयास करेंगे। पहला सेवा स्मार्ट होम डिवाइस की टेलीमेट्री क्वेरी कर सकती है, जिससे आपको होम असिस्टेंट से रिमोटली डेटा प्राप्त करने की अनुमति मिलती है। दूसरी सेवा आपके होम असिस्टेंट कॉन्फ़िगरेशन का बैकअप बनाती है और जब आवश्यक होता है तो इसे बहाल करती है (उदाहरण के लिए, एसडी कार्ड के विफलता के मामले में)।\n\n\n## पैराचैन कार्यों के बारे में\n\nअगले आप देखेंगे कि रोबोनॉमिक्स पैराचैन के कार्यों का उपयोग कैसे किया जाता है ाकि होम असिस्टेंट उपयोगकर्ता को आवश्यक सेवा प्रदान की जा सके। \n\nटेलीमेट्री प्राप्त करने का आधार <code>datalog</code> पैलेट पर है जिसे आप पहले से जानते हैं। निश्चित समयावधि के बाद (लेकिन जमा वजन की अनुमति देती है), <code>datalog.record()</code> लेन-देन <code>SUB_CONTROLLER</code> पते से पैराचैन को भेजा जाता है जिसमें एन्क्रिप्टेड फ़ाइल का आईपीएफएस हैश होता है, जिसमें आपके आईओटी डिवाइस के सभी डेटा एकत्र किया जाता है। वास्तव में टेलीमेट्री प्राप्त करने के लिए, आप पैराचैन से अपनी आईओटी सब्सक्रिप्शन से संबंधित आवश्यक डेटालॉग का अनुरोध करते हैं और फिर अपनी कुंजी के साथ उनहें डिक्रिप्ट करते हैं।\n\nबैकअप बनाने के लिए, एक और रोबोनॉमिक्स पैलेट जिसे <code>digitalTwin</code> कहा जाता है, का उपयोग किया जाता है, जो एक डिजिटल ट्विन की विचार की कार्यान्वयन है, एक वास्तविक उपकरण की डिजिटल संस्करण जो इसकी तकनीकी विशेषताओं और ऐतिहासिक डेटा की प्रतिलिपि बनाता है। पहले, एक अद्वितीय आईडी बनाया जाता है आपके होम असिस्टेंट के डिजिटल ट्विन के लिए <code>digitalTwin.create()</code> एक्सट्रिंसिक का उपयोग करके। फिर, <code>digitalTwin.setSource()</code> एक्सट्रिंसिक का उपयोग करके, इस आईडी को कुछ डेटा (जैसे <code>topic</code> फ़ील्ड) और पैराचैन में एक पते (जैसे <code>source</code> फ़ील्ड) के साथ ांधा जाता है। होम असिस्टेंट बैकअप के लिए, बैकअप फ़ाइल का हैश <code>topic</code> में संग्रहित होता है, और <code>SUB_OWNER</code> पता <code>source</code> में संग्रहित होता है।\n\n## निर्देश\n\n<List type=\"numbers\">\n\n<li>\n\nटेलीमेट्री प्राप्त करना\n\n<List>\n\n\n<li>\n\ndapp पर जाएं और [स्मार्टहोम टेलीमेट्री](https://dapp.robonomics.network/#/smarthome-telemetry) सेवा चुनें।\n\n<LessonVideo  :videos=\"[{src: 'https://crustipfs.info/ipfs/Qmao9RoWcKo2qs4PAGtm5gqHzyAHJcpDqNLgciU35FJeVm', type:'mp4'}]\" />\n\n</li>\n\n<li>\n\n<code>CONTROLLER</code> फ़ील्ड में <code>SUB_CONTROLLER</code> पता दर्ज करें। डेटा एन्क्रिप्ट करने के लिए सीड फ़्रेज डालें।\n\n</li>\n\n<li>\n\n<code>Get telemetry</code> ब्लॉक में ड्रॉप-डाउन सूची से एक टाइमस्टैम्प चुनें और <code>DOWNLOAD TELEMETRY</code> बटन दबाएं।\n\n\nटेलीमेट्री डाउनलोड करने में कुछ समय लग सकता है। समाप्त होने के बाद, आप अपने सेंसर्स से जानकारी देखेंगे\n\n</li>\n</List>\n</li>\n\n\n<li>\n\nबैकअ बनाना\n\n<List>\n\n<li>\n\nबैकअप बनाने के लिए, एक सेवा को कॉल किया जाता है जो कॉन्फ़िगरेशन फ़ाइलों के साथ एक सुरक्षित आर्काइव उत्पन्न करती है। इस सेवा फिर आर्काइव को IPFS में जोड़ती है और परिणामी CID को Robonomics डिजिटल ट्विन में स्टोर करती है।\n\n<robo-academy-note type=\"warning\" title=\"चेतावनी\">\nअपनी कॉन्फ़िगरेशन को पुनर्स्थापित करने के लिए, एक कस्टम IPFS गेटवे जैसे Pinata (pinata.cloud) या Crust Network (crust.network) का उपयोग करना आवश्यक है। इसके बिना, आपकी बैकअप केवल आपके स्थानीय IPFS नोड पर स्टोर की जाएगी, जिससे आपको स्थानीय नोड असफल होने की स्थिति में अपनी होम असिस्टेंट कॉन्फ़िगरेशन को पुनर्स्थापित करने से रोक सकता है। \n</robo-academy-note>\n\n<LessonVideo  :videos=\"[{src: 'https://crustipfs.info/ipfs/QmVo91dLaAYgFDM1vrL2PYfAffM6SGGC59ZERbfHR44tqW', type:'mp4'}]\" />\n\n</li>\n\n<li>\n\nहोम असिस्टेंट के वेब इंटरफ़ेस में जाएं <code>Developer Tools</code> -> <code>Services</code>। <code>Robonomics: Save Backup to Robonomics</code> खोजें और <code>CALL SERVICE</code> दबाएं।\n\n</li>\n\n<li>\n\nजब तक आप <code>Backup was updated in Robonomics</code> अधिसूचना <code>Notification</code> में दिखाई नहीं देती, तब तक प्रतीक्षा करें।\n\n</li>\n\n<li>\n\nअपनी कॉन्फ़िगरेशन को पुनर्स्थापित करने के लिए, आपको एक नया होम असिस्टेंट इंस्टेंस स्थापित करने की आवश्यकता होगी (और सभी पिछले कदम दोहराने होंगे) जिसमें रोबोनॉमिक्स होम असिस्टेंट एकीकरण का उपयोग करते हुए पहले बनाए गए सीड्स का उपयोग करना होगा। आपको एक MQTT ब्रोकर भी सेटअप करना होगा जिसमे एक ही उपयोगकर्ता नाम और पासवर्ड हो।\n\n<robo-academy-note type=\"warning\" title=\"चेतावनी\">\nक्योंकि कुछ डिवाइसेज जो वाई-फाई या MQTT के माध्यम से होम असिस्टेंट से कनेक्ट हैं, आपको अपने रास्पबेरी पाई के स्थानीय IP पते को स्पष्ट रूप से निर्दिष्ट करने की आवश्यकता होती है, जब बैकअप को पुनर्स्थापित किया जाता है, तो इन्हें इस IP में परिवर्तन के कारण उपलब्ध नहीं हो सकता। आपको इन डिवाइसेज की सेटिंग्स में नए IP पते को दोबारा दर्ज करने की आवश्यकता होगी। इसे रोकने के लिए, अपने राउटर सेटिंग्स में अपने रास्पबेरी पाई के लिए एक स्थिर स्थानीय IP सेटअप कर सकते हैं (यदि यह सुविधा समर्थित करता है)।\n</robo-academy-note>\n\n<LessonVideo  :videos=\"[{src: 'https://crustipfs.info/ipfs/QmWmnmkXUcPXsAnQzwN3UEuki2GMYnQDx3vhgjEypCU8aR', type:'mp4'}]\" />\n\n\n</li>\n\n<li>\n\nहोम अिस्टेंट के वेब इंटरफेस में जाएं <code>Developer Tools</code> -> <code>Services</code>। <code>Robonomics: Restore from the Backup in Robonomics</code> खोजें और <code>CALL SERVICE</code> दबाएं। अपने बैकअप की स्थिति जांचने के लिए <code>Overview</code> पेज पर जाएं।\n\n</li>\n\n<li>\n\nहोम असिस्टेंट को पुनः आरंभ करने के बाद, आपका कॉन्फ़िगरेशन पुनर्स्थापित हो जाएगा। अगर स्थिति <code>restored</code> में बदल जाती है लेकिन होम असिस्टेंट स्वचालित रूप से पुनः आरंभ नहीं होता है, तो आपको <<code>Settings</code> > <code>System</code> पर जाकर ऊपर दाएं कोने में <code>RESTART</code> बटन पर क्लिक करके इसे मैन्युअल रूप से रीस्टार्ट करना होग।\n\n</li>\n\n</List>\n</li>\n\n</List>\n\n## पाठ्यक्रम पूरा करना\n\n<List>\n\n<li class=\"flex\"> \n\nबधाई हो! आपने अपने सामरिक स्मार्ट होम की पूरी सेटअप और डिप्लॉयमेंट सफलतापूर्वक पूरा किया है। आप अब हमसे एक पाठ्यक्रम समापन प्रमाणपत्र का अनुरोध कर सकते हैं हमारे डिस्कॉर्ड-चैनल पर जाकर। हमें  [robonomics-academy](https://discord.com/channels/803947358492557312/803947358492557315) चैट में लिखें और हमारा प्रतिनिधि आपसे संपर्क करेगा।\n</li>\n\n<li class=\"flex\">\n\nपाठ्यक्रम समापन का प्रमाण उन संबंधित लेन-देन हैं जो [पॉल्काडॉट एक्सप्लोरर](https://robonomics.subscan.io/) में सत्यापित किए जा सकते हैं। ये लेन-देन एक सब्सक्रिप्शन खरीदने, एक डिवाइस को सब्सक्रिप्शन में जोड़ने और डिवाइस से डेटालॉग भेजने के बारे में हैं।\n\n</li>\n\n</List>","fileInfo":{"path":"hi/learn/smart-home-course/usage-of-robonomics-with-hass.md","name":"usage-of-robonomics-with-hass"},"defaultName":"Sovereign Smart Home with Robonomics and Home Assistant","lastUpdate":"Thu May 18 2023 10:46:29 GMT+0400 (Samara Standard Time)"}},"context":{}}