{"hash":"747fe7ef75ee9f5c9a3260f3225c1f4d5c548a18","data":{"course":{"id":"ef6fc952e2514029bb6f7d6668609716","title":"ุงูุฏุฑุณ #1ุ ุงูุจุซ ูู ุฎูุงู ุงููุฑุขุฉ ุงูุณูุฏุงุก","description":"ุณูุนููู ูุฐุง ุงูุฏุฑุณ ุงูุงูุชุชุงุญู ุงูุฃุณุงููุจ ุงูุฃุณุงุณูุฉ ููุชูุงุนู ูุน ุชุทุจูู ูุฑูุฒู (ุฃู dapp) ููุฒุน.","content":"\n## ููุฏูุฉ\n\nุณูุนููู ูุฐุง ุงูุฏุฑุณ ุงูุงูุชุชุงุญู ุงูุฃุณุงููุจ ุงูุฃุณุงุณูุฉ ููุชูุงุนู ูุน **ุชุทุจูู ูุฑูุฒู (ุฃู dapp)**. ููุฐุง ุงูุบุฑุถุ ูููุง ุจุฅูุดุงุก ุชุทุจูู ูุฑูุฒู ุฎุงุต ูุณูู \"ุจุซ ุงููุฑุขุฉ ุงูุณูุฏุงุก\"ุ ุงูุฐู ูุนูู ูุจุงุดุฑุฉ ูู ูุชุตูุญ ุงูููุจ ุงูุฎุงุต ุจู ููุธูุฑ ุจุซูุง ูุน ุชููุฒููู ุฑูุชุฑู ุตุบูุฑ. ูููู ููุชุทุจูู ุงูุชุญูู ุนู ุจุนุฏ ูู ุงูุชููุฒููู ูุชุบููุฑ ุฑูุฒ ุงูุงุณุชุฌุงุจุฉ ุงูุณุฑูุนุฉ ุนู ุทุฑูู ุฅุฑุณุงู ุฑุณุงูุชู ุจุงุณุชุฎุฏุงู ููุตุฉ Robonomics.\n\n## ุงูุฅููุงู\n\nูููุง ุจุฅูุด๏ฟฝ๏ฟฝุก ูุฐุง ุงูุชุทุจูู ุงููุฑูุฒู ุจูุฏู ุชููุฆุฉ ุงููุฒุงุฌ ุงูุตุญูุญ ูุจููุฉ ุงูุฏูุฑุฉ. ุชููู ููุฑุฉ ุงูุชุทุจูู ุงููุฑูุฒู ุฑูุญ ุงูุฏุณุชูุจูุง ุงูุชู ุชุนูุด ูููุง ูุนุธู ุญูุงุฉ ุงูุฅูุณุงู ุนูู ุดุงุดุฉ ุณูุฏุงุก ููููู ููุฌููุน ุงูุชุฌุณุณ ุนูู ูุฐู ุงูุญูุงุฉ.\n\nุฏุฎูุช ุงูุชูููููุฌูุง ุจุดูู ูุง ุฑุฌุนุฉ ููู ุฅูู ุญูุงุฉ ุงูุฅูุณุงู ุงูููููุฉ ูุบุงูุจูุง ูุง ุชุชุดุงุจู ุงูุชูููููุฌูุง ูุน ุญูุงุชูุง ุจุดูู ุฃุนูู ููุง ูุฑุบุจ ุจุนุถูุง. ููุงู ุณุคุงู ูุฏูู ูุตุนุจ ูู ูุฌุงู ุงูููุณูุฉ ุญูู ููุงููุฉ ุงูุฃุฌุฒุงุก ุงูุนุงูุฉ ูุงูุฎุงุตุฉ ูู ูุฌูุฏ ุงูุฅูุณุงู. ููุฐุง ุงูุณุจุจ ูุฑูุฏ ูู Robonomics ุชูููุฐ ุฃุฏูุงุช ุงูููุจ3 ูู ูุฌุงู ุงูุฅูุชุฑูุช ุงูุฃุดูุงุก. ูุฑูุฏ ุฌุนูู ูู ุงููุณุชุญูู ุชุบููุฑ ุงุณู ูู ุดุฎุต ุนูู ูููุจ ุงูุฃุฑุถ ููุฑูุง ุฅูู ุฑูุฒ ุชุนุฑูู ุฏูู ููุงููุฉ ุงูุดุฎุต.\n\nุชูููุงุช ุงูุฅูุชุฑูุช ูู ุงูุฌูู ุงููุงุฏู ูููู ุฃู ุชุณุงุนุฏ ูู ุชุญุณูู ุงูุนูุงูุฉ ุจูู ุงููุงุณ ูุงูุขูุงุชุ ูุฌุนู ุงูุฃุฌูุฒุฉ ุงูุฐููุฉ ุฃูุซุฑ ุงุณุชููุงููุฉ ูุฃุณุฑุน ูู ุชูุฏูู ุงูุฎุฏูุงุช ูููุงุณุ ูุงูุฃูู ูู ุฐููุ ุฌุนู ูู ุงููุณุชุญูู ุงูุณูุทุฑุฉ ุนูู ุฌููุน ุงููุงุณ ุจูุณุงุนุฏุฉ ุงูุขูุงุช. ูุฐู ูู ุงูุณููุงุฑูู ุงููุซุงูู ุงูุฐู ูุฑุงู ูุฏูุฌ ุงูุฑูุจูุชุงุช ูู ุญูุงุฉ ุงูุจุดุฑ ุงูููููุฉ.\n\n## ุงูุชุนูููุงุช\n\n<List type=\"numbers\">\n\n<li>\n\nูู ุจุชุซุจูุช ุฅุถุงูุฉ ูุชุตูุญ Polkadot.js ูุฅูุดุงุก ุญุณุงุจ ูู Robonomics Parachain.\n\nุงูุธุฑ ุฅูู ุงูุฏููู ุนูู ููููุจูุฏูุง ูุฏููุง: [ุฅูุดุงุก ุญุณุงุจ ูู Robonomics Parachain](https://wiki.robonomics.netwุฃูk/docs/create-account-in-dapp/). ุนููู ุฃู ุชุฌุชุงุฒ ุฌููุน ุฏุฑูุณ ุงูุฏูุฑุฉ ุจุญุณุงุจ ูุงุญุฏ ูู Polkadot ููุชูุฏู ุจุทูุจ ููุญุตูู ุนูู ุงูุดูุงุฏุฉ.\n\n</li>\n\n<li>\n\nุงูุถู ุฅูู ุฎุงุฏููุง ุนูู [Discุฃูd](https://discุฃูd.gg/xqDgG3EGm9) ูุงุญุตู ุนูู ุฏูุฑ \"ุนุถู ูู ูุฌุชูุน ุงููุทูุฑูู\". ููููุงู ุจุฐููุ ูู ุงูููุงุฉ \"๐welcome-info\" ุนููู ุงูููุฑ ุนูู ุงูุฑูุฒ ุงูุชุนุจูุฑู ุงูููุงุจู (โ๏ธ) ูู ููุดูุฑ ุงูุฑูุจูุช MEE6.\n\n</li>\n\n<li>\n\nุงุจุญุซ ุนู ุงูุฑูุจูุช ุงูุฏุฑุฏุดุฉ ุงูุฎุงุตุฉ [Discord](https://discord.com/channels/803947358492557312/944186892038053899)ุ ุงููุณูู \"๐ฐacademy-faucet\" ูู ูุงุฆูุฉ ุงููููุงุช ูุฃุฏุฎู ุนููุงูู ูู Robonomics Parachain ูู ุชูุฏูุฏ Polkadot.js.\n\nุชุฃูุฏ ูู ุฅุฑุณุงู ุงูุนููุงู ุฅูู ุงูุฑูุจูุช ุจุงูุชูุณูู ุงูุตุญูุญ (ูุจุฏุฃ ุจู \"4\"). ุฅุฐุง ูู ูุณุชุฌุจ ุงูุฑูุจูุช ุฃู ูู ูุถูู ุนููุงูู ุฅูู ุงูุงุดุชุฑุงู ูู ุงููุฑุฉ ุงูุฃูููุ ุฌุฑุจ ุนุฏุฉ ูุฑุงุช ุฃุฎุฑูุ ูุญุฏุซ ูุฐุง ุจุณุจุจ ุญูู ุงูุดุจูุฉ. ุฅุฐุง ุงุณุชูุฑุช ุงููุดููุฉุ ุงุณุฃู ูู ุงูููุงุฉ \"๐robonomics-academy\".\n\n</li>\n\n<li>\n\nุงูุชูู ุฅูู ุชุทุจูู [Black Mirror dapp](https://blackmirror.robonomics.academy) ูุงุณูุญ ููุชุทุจูู ุจุงููุตูู ุฅูู ุชูุฏูุฏ Polkadot.js.\n\nุชุฃูุฏ ูู ุงุฎุชูุงุฑ ุงูุญุณุงุจ ุงูุตุญูุญ ุงูุฐู ุญุตู ุนูู ุงุดุชุฑุงู IoT ูุฌุงูู.\n\n</li>\n\n<li>\nุฃุฏุฎู ูู ุงูุชุทุจูู ุฑุณุงูุชู ุงููุตูุฉ ุงููุตูุฑุฉ (ุจุงูุฅูุฌููุฒูุฉ) ูุงููุฑ ุนูู ุฒุฑ \"ุชูููุน ูุฅุฑุณุงู\". \n</li>\n\n<li>\nูู ูุงูุฐุฉ ุงูุงูุชุฏุงุฏ ุงูุชู ุธูุฑุชุ ุฃุฏุฎู ูููุฉ ุงููุฑูุฑ ุงูุฎุงุตุฉ ุจู ููู ุจุงูุชูููุน ุนูู ุงููุนุงููุฉ.\n</li>\n\n<li>\nุชุฃูุฏ ูู ุฃู ุชู ุฅุฑุณุงู ุนูููุชู ุจูุฌุงุญ ุนู ุทุฑูู ุงูุชุญูู ูู ุงูุฑุงุจุท ุฅูู ูุณุชูุดู Polkadot.\n\nูุฌุจ ุฃู ูุธูุฑ ุงูุญูู <code>ุงููุชูุฌุฉ</code> ูู <code>ูุฌุงุญ</code>.\n</li>\n\n<li>\nุชุญูู ูู ุฑูุฒ ุงูุงุณุชุฌุงุจุฉ ุงูุณุฑูุนุฉ ุนูู ุดุงุดุฉ ุงูุชููุงุฒุ ูุฌุจ ุฃู ูุชุบูุฑ (ูุฏ ูุณุชุบุฑู ุญุชู 2 ุฏูููุฉ).\n</li>\n</List>\n\n<Result>\n\nุณูุชู ุงุนุชุจุงุฑ ุงูุฏุฑุณ ููุชููุงู ุจุนุฏ ุฅุฑุณุงู ูุนุงููุฉ ูุงุฌุญุฉ ูุธููุฑูุง ูู ูุณุชูุดู Polkadot ูุญุณุงุจู ูู Polkadot.js.\n\nููููู ุงูุชุญูู ูู ูุชุงุฆุฌู ุนูู [ุงูุชุทุจูู ุงูุฎุงุต ุจุงูุชุญูู](https://lk.robonomics.academy/). ููุชูููุถ ูู ุงูุชุทุจูู ุงูุฎุงุต ุจุงูุชุญููุ ุงุณุชุฎุฏู ููุณ ุงูุญุณุงุจ ูู Polkadot.js ุงูุฐู ุชู ุงุณุชุฎุฏุงูู ุฎูุงู ุงูุฏูุฑุฉ.\n\n</Result>\n","fileInfo":{"path":"ar/learn/introduction-course/broadcasting-through-the-black-mirror.md","name":"broadcasting-through-the-black-mirror"},"defaultName":"Introduction to the ideas of Robonomics","lastUpdate":"Thu May 04 2023 12:53:51 GMT+0400 (Samara Standard Time)"}},"context":{}}